matematikk_test/__init__.py
matematikk_test/example.py
matematikk_test-0.0.10.dist-info/LICENCE
matematikk_test-0.0.10.dist-info/METADATA
matematikk_test-0.0.10.dist-info/WHEEL
matematikk_test-0.0.10.dist-info/top_level.txt
matematikk_test-0.0.10.dist-info/RECORD
