Metadata-Version: 2.1
Name: matematikk_test
Version: 0.0.10
Summary: matematikk_test
Author-email: matematikk_test <kontakt@matematikk.as>
Project-URL: Homepage, https://github.com/pypa/sampleproject
Project-URL: Issues, https://github.com/pypa/sampleproject/issues
Classifier: Programming Language :: Python :: 3
Classifier: License :: OSI Approved :: MIT License
Classifier: Operating System :: OS Independent
Requires-Python: >=3.8
License-File: LICENCE
